CHANGELOG
LICENSE
MANIFEST.in
README.rst
setup.py
django_permissions_widget.egg-info/PKG-INFO
django_permissions_widget.egg-info/SOURCES.txt
django_permissions_widget.egg-info/dependency_links.txt
django_permissions_widget.egg-info/not-zip-safe
django_permissions_widget.egg-info/top_level.txt
permissions_widget/__init__.py
permissions_widget/__init__.pyc
permissions_widget/admin.py
permissions_widget/admin.pyc
permissions_widget/forms.py
permissions_widget/forms.pyc
permissions_widget/layout.py
permissions_widget/settings.py
permissions_widget/settings.pyc
permissions_widget/__pycache__/__init__.cpython-35.pyc
permissions_widget/__pycache__/__init__.cpython-36.pyc
permissions_widget/__pycache__/__init__.cpython-37.pyc
permissions_widget/__pycache__/admin.cpython-35.pyc
permissions_widget/__pycache__/admin.cpython-36.pyc
permissions_widget/__pycache__/admin.cpython-37.pyc
permissions_widget/__pycache__/forms.cpython-35.pyc
permissions_widget/__pycache__/forms.cpython-36.pyc
permissions_widget/__pycache__/forms.cpython-37.pyc
permissions_widget/__pycache__/layout.cpython-35.pyc
permissions_widget/__pycache__/layout.cpython-36.pyc
permissions_widget/__pycache__/layout.cpython-37.pyc
permissions_widget/__pycache__/settings.cpython-35.pyc
permissions_widget/__pycache__/settings.cpython-36.pyc
permissions_widget/__pycache__/settings.cpython-37.pyc
permissions_widget/templates/permissions_widget/crispy_field.html
permissions_widget/templates/permissions_widget/widget.html
permissions_widget/templatetags/__init__.py
permissions_widget/templatetags/__init__.pyc
permissions_widget/templatetags/permissions_widget_tags.py
permissions_widget/templatetags/permissions_widget_tags.pyc
permissions_widget/templatetags/__pycache__/__init__.cpython-35.pyc
permissions_widget/templatetags/__pycache__/__init__.cpython-36.pyc
permissions_widget/templatetags/__pycache__/__init__.cpython-37.pyc
permissions_widget/templatetags/__pycache__/permissions_widget_tags.cpython-35.pyc
permissions_widget/templatetags/__pycache__/permissions_widget_tags.cpython-36.pyc
permissions_widget/templatetags/__pycache__/permissions_widget_tags.cpython-37.pyc