Metadata-Version: 1.1
Name: django-permissions-widget
Version: 1.5.2
Summary: Fresh Django permissions widget
Home-page: http://django-permissions-widget.rtfd.org
Author: James Pic
Author-email: jamespic@gmail.com
License: MIT
Keywords: django permissions widget
Platform: UNKNOWN
Classifier: Development Status :: 1 - Planning
Classifier: Environment :: Web Environment
Classifier: Framework :: Django
Classifier: Intended Audience :: Developers
Classifier: License :: OSI Approved :: MIT License
Classifier: Operating System :: OS Independent
Classifier: Programming Language :: Python
Classifier: Programming Language :: Python :: 2
Classifier: Programming Language :: Python :: 3
Classifier: Topic :: Internet :: WWW/HTTP
Classifier: Topic :: Software Development :: Libraries :: Python Modules
